experiments/README.md
experiments/__init__.py
experiments/brandl_experiment.py
experiments/keller_rady_experiment.py
experiments/keller_rady_sweep.py
experiments/run_experiment.py
polaris/__init__.py
polaris/experiments.py
polaris/py.typed
polaris/simulation.py
polaris/agents/__init__.py
polaris/agents/base.py
polaris/agents/polaris_agent.py
polaris/agents/components/__init__.py
polaris/agents/components/belief.py
polaris/agents/components/critics.py
polaris/agents/components/inference.py
polaris/agents/components/policy.py
polaris/agents/memory/__init__.py
polaris/agents/memory/replay_buffer.py
polaris/algorithms/__init__.py
polaris/algorithms/regularization/__init__.py
polaris/algorithms/regularization/ewc.py
polaris/algorithms/regularization/si.py
polaris/config/__init__.py
polaris/config/args.py
polaris/config/defaults.py
polaris/config/experiment_config.py
polaris/environments/__init__.py
polaris/environments/base.py
polaris/environments/social_learning.py
polaris/environments/strategic_exp.py
polaris/networks/__init__.py
polaris/networks/gnn.py
polaris/networks/mlp.py
polaris/networks/transformer.py
polaris/training/__init__.py
polaris/training/evaluator.py
polaris/training/trainer.py
polaris/utils/__init__.py
polaris/utils/device.py
polaris/utils/encoding.py
polaris/utils/io.py
polaris/utils/math.py
polaris/utils/metrics.py
polaris/visualization/__init__.py
polaris/visualization/si_analysis.py
polaris/visualization/plots/__init__.py
polaris/visualization/plots/allocations.py
polaris/visualization/plots/beliefs.py
polaris/visualization/plots/learning_curves.py
polaris/visualization/styles/__init__.py
polaris/visualization/styles/latex.py
polaris_marl-2.0.2.dist-info/licenses/LICENSE
scripts/build_and_publish.py
polaris_marl-2.0.2.dist-info/METADATA
polaris_marl-2.0.2.dist-info/WHEEL
polaris_marl-2.0.2.dist-info/entry_points.txt
polaris_marl-2.0.2.dist-info/top_level.txt
polaris_marl-2.0.2.dist-info/RECORD
