Metadata-Version: 2.4
Name: polaris-marl
Version: 2.0.2
Summary: POLARIS: Partially Observable Learning with Active Reinforcement In Social Environments
Home-page: https://github.com/ecdogaroglu/polaris
Author: Ege Can Doğaroğlu
Author-email: Ege Can Doğaroğlu <ege.dogaroglu@example.com>
Maintainer-email: Ege Can Doğaroğlu <ege.dogaroglu@example.com>
License: MIT
Project-URL: Homepage, https://github.com/ecdogaroglu/polaris
Project-URL: Documentation, https://github.com/ecdogaroglu/polaris#documentation
Project-URL: Repository, https://github.com/ecdogaroglu/polaris
Project-URL: Bug Tracker, https://github.com/ecdogaroglu/polaris/issues
Keywords: multi-agent,reinforcement-learning,social-learning,graph-neural-networks,pytorch,partially-observable,game-theory
Classifier: Development Status :: 4 - Beta
Classifier: Intended Audience :: Science/Research
Classifier: Topic :: Scientific/Engineering :: Artificial Intelligence
Classifier: License :: OSI Approved :: MIT License
Classifier: Programming Language :: Python :: 3
Classifier: Programming Language :: Python :: 3.8
Classifier: Programming Language :: Python :: 3.9
Classifier: Programming Language :: Python :: 3.10
Classifier: Programming Language :: Python :: 3.11
Classifier: Operating System :: OS Independent
Classifier: Environment :: GPU :: NVIDIA CUDA
Classifier: Environment :: MacOS X
Requires-Python: >=3.8
License-File: LICENSE
Requires-Dist: torch>=1.8.0
Requires-Dist: numpy>=1.20.0
Requires-Dist: matplotlib>=3.4.0
Requires-Dist: networkx>=2.6.0
Requires-Dist: scikit-learn>=1.0.0
Requires-Dist: tqdm>=4.60.0
Requires-Dist: scipy>=1.7.0
Requires-Dist: pandas>=1.3.0
Requires-Dist: seaborn>=0.11.0
Provides-Extra: gnn
Requires-Dist: torch-geometric>=2.0.0; extra == "gnn"
Requires-Dist: torch-scatter>=2.0.9; extra == "gnn"
Requires-Dist: torch-sparse>=0.6.13; extra == "gnn"
Requires-Dist: torch-cluster>=1.6.0; extra == "gnn"
Requires-Dist: torch-spline-conv>=1.2.1; extra == "gnn"
Provides-Extra: dev
Requires-Dist: pytest>=6.0.0; extra == "dev"
Requires-Dist: pytest-cov>=2.12.0; extra == "dev"
Requires-Dist: black>=21.0.0; extra == "dev"
Requires-Dist: flake8>=3.9.0; extra == "dev"
Requires-Dist: isort>=5.9.0; extra == "dev"
Requires-Dist: mypy>=0.910; extra == "dev"
Requires-Dist: pre-commit>=2.15.0; extra == "dev"
Provides-Extra: docs
Requires-Dist: sphinx>=4.0.0; extra == "docs"
Requires-Dist: sphinx-rtd-theme>=0.5.0; extra == "docs"
Requires-Dist: sphinx-autodoc-typehints>=1.12.0; extra == "docs"
Provides-Extra: all
Requires-Dist: torch-geometric>=2.0.0; extra == "all"
Requires-Dist: torch-scatter>=2.0.9; extra == "all"
Requires-Dist: torch-sparse>=0.6.13; extra == "all"
Requires-Dist: torch-cluster>=1.6.0; extra == "all"
Requires-Dist: torch-spline-conv>=1.2.1; extra == "all"
Requires-Dist: pytest>=6.0.0; extra == "all"
Requires-Dist: pytest-cov>=2.12.0; extra == "all"
Requires-Dist: black>=21.0.0; extra == "all"
Requires-Dist: flake8>=3.9.0; extra == "all"
Requires-Dist: isort>=5.9.0; extra == "all"
Requires-Dist: mypy>=0.910; extra == "all"
Requires-Dist: pre-commit>=2.15.0; extra == "all"
Requires-Dist: sphinx>=4.0.0; extra == "all"
Requires-Dist: sphinx-rtd-theme>=0.5.0; extra == "all"
Requires-Dist: sphinx-autodoc-typehints>=1.12.0; extra == "all"
Dynamic: author
Dynamic: home-page
Dynamic: license-file
Dynamic: requires-python
